{
  "timestamp": "2026-03-19T22:07:41.927427",
  "market_summary": {
    "total_market_cap": 2434695391274,
    "total_volume_24h": 172997748812.0,
    "total_coins_tracked": 100,
    "market_cap_change_24h": -0.21,
    "volume_change_24h": 0.0,
    "timestamp": "2026-03-19T22:07:41.926932"
  },
  "trending_coins": [
    {
      "symbol": "BTC",
      "name": "Bitcoin",
      "price": 70325,
      "change24h": -1.00039,
      "marketCap": 1406776357920,
      "volume24h": 45835893457,
      "ath": 126080,
      "ath_change_percentage": -44.22192,
      "sparkScore": 55,
      "circulating_supply": 20003043.0,
      "total_supply": 20003043.0
    },
    {
      "symbol": "ETH",
      "name": "Ethereum",
      "price": 2144.92,
      "change24h": -2.19974,
      "marketCap": 258855171414,
      "volume24h": 24223220671,
      "ath": 4946.05,
      "ath_change_percentage": -56.63366,
      "sparkScore": 68,
      "circulating_supply": 120691801.1632979,
      "total_supply": 120691801.1632979
    },
    {
      "symbol": "USDT",
      "name": "Tether",
      "price": 1.0,
      "change24h": 0.01403,
      "marketCap": 184118402139,
      "volume24h": 76943301106,
      "ath": 1.32,
      "ath_change_percentage": -24.40882,
      "sparkScore": 62,
      "circulating_supply": 184092103149.706,
      "total_supply": 189559041966.2262
    },
    {
      "symbol": "XRP",
      "name": "XRP",
      "price": 1.45,
      "change24h": -0.72609,
      "marketCap": 88954959088,
      "volume24h": 2631447438,
      "ath": 3.65,
      "ath_change_percentage": -60.17012,
      "sparkScore": 50,
      "circulating_supply": 61227832454.0,
      "total_supply": 99985701766.0
    },
    {
      "symbol": "BNB",
      "name": "BNB",
      "price": 641.28,
      "change24h": -1.52748,
      "marketCap": 87446882976,
      "volume24h": 1082202936,
      "ath": 1369.99,
      "ath_change_percentage": -53.19095,
      "sparkScore": 51,
      "circulating_supply": 136357724.82,
      "total_supply": 136357724.82
    },
    {
      "symbol": "USDC",
      "name": "USDC",
      "price": 0.999908,
      "change24h": -0.00265,
      "marketCap": 79237307963,
      "volume24h": 6254423340,
      "ath": 1.043,
      "ath_change_percentage": -4.16955,
      "sparkScore": 57,
      "circulating_supply": 79241721014.62352,
      "total_supply": 79242103272.56729
    },
    {
      "symbol": "SOL",
      "name": "Solana",
      "price": 89.05,
      "change24h": -1.36067,
      "marketCap": 50949531738,
      "volume24h": 3550987332,
      "ath": 293.31,
      "ath_change_percentage": -69.63982,
      "sparkScore": 60,
      "circulating_supply": 571567565.2857559,
      "total_supply": 571567585.9824531
    },
    {
      "symbol": "TRX",
      "name": "TRON",
      "price": 0.303476,
      "change24h": -0.21076,
      "marketCap": 28753181448,
      "volume24h": 539098070,
      "ath": 0.431288,
      "ath_change_percentage": -29.63502,
      "sparkScore": 45,
      "circulating_supply": 94751085019.1791,
      "total_supply": 94751265525.2406
    },
    {
      "symbol": "FIGR_HELOC",
      "name": "Figure Heloc",
      "price": 1.033,
      "change24h": 1.03121,
      "marketCap": 16364027615,
      "volume24h": 30110241,
      "ath": 1.049,
      "ath_change_percentage": -1.55054,
      "sparkScore": 39,
      "circulating_supply": 15843541913.347,
      "total_supply": 15843541913.347
    },
    {
      "symbol": "DOGE",
      "name": "Dogecoin",
      "price": 0.093536,
      "change24h": -1.65593,
      "marketCap": 14357853955,
      "volume24h": 943990917,
      "ath": 0.731578,
      "ath_change_percentage": -87.21452,
      "sparkScore": 55,
      "circulating_supply": 153478026383.7052,
      "total_supply": 153478756383.7052
    },
    {
      "symbol": "WBT",
      "name": "WhiteBIT Coin",
      "price": 55.54,
      "change24h": -2.59681,
      "marketCap": 11853191306,
      "volume24h": 77011232,
      "ath": 64.11,
      "ath_change_percentage": -13.33276,
      "sparkScore": 47,
      "circulating_supply": 213418274.0,
      "total_supply": 319918274.0
    },
    {
      "symbol": "USDS",
      "name": "USDS",
      "price": 0.999975,
      "change24h": 0.00916,
      "marketCap": 11460579431,
      "volume24h": 11556756,
      "ath": 1.057,
      "ath_change_percentage": -5.37022,
      "sparkScore": 37,
      "circulating_supply": 11460873503.22658,
      "total_supply": 11460873503.22658
    },
    {
      "symbol": "ADA",
      "name": "Cardano",
      "price": 0.267157,
      "change24h": -2.33154,
      "marketCap": 9845310690,
      "volume24h": 428424077,
      "ath": 3.09,
      "ath_change_percentage": -91.34548,
      "sparkScore": 48,
      "circulating_supply": 36846946339.91323,
      "total_supply": 45000000000.0
    },
    {
      "symbol": "HYPE",
      "name": "Hyperliquid",
      "price": 39.18,
      "change24h": -7.4432,
      "marketCap": 9342787522,
      "volume24h": 438605491,
      "ath": 59.3,
      "ath_change_percentage": -33.93501,
      "sparkScore": 54,
      "circulating_supply": 238385315.9541414,
      "total_supply": 962274028.9541414
    },
    {
      "symbol": "BCH",
      "name": "Bitcoin Cash",
      "price": 455.44,
      "change24h": -0.32567,
      "marketCap": 9114211573,
      "volume24h": 199817086,
      "ath": 3785.82,
      "ath_change_percentage": -87.96982,
      "sparkScore": 50,
      "circulating_supply": 20009618.64665078,
      "total_supply": 20009899.89665078
    },
    {
      "symbol": "LEO",
      "name": "LEO Token",
      "price": 9.17,
      "change24h": 1.10423,
      "marketCap": 8442927149,
      "volume24h": 1297364,
      "ath": 10.14,
      "ath_change_percentage": -9.53238,
      "sparkScore": 32,
      "circulating_supply": 921076216.9,
      "total_supply": 985239504.0
    },
    {
      "symbol": "LINK",
      "name": "Chainlink",
      "price": 9.07,
      "change24h": -1.53608,
      "marketCap": 6426622194,
      "volume24h": 389547793,
      "ath": 52.7,
      "ath_change_percentage": -82.77955,
      "sparkScore": 53,
      "circulating_supply": 708099970.4525867,
      "total_supply": 1000000000.0
    },
    {
      "symbol": "XMR",
      "name": "Monero",
      "price": 339.88,
      "change24h": -1.30329,
      "marketCap": 6269667808,
      "volume24h": 77221341,
      "ath": 797.73,
      "ath_change_percentage": -57.39444,
      "sparkScore": 48,
      "circulating_supply": 18446744.07370955,
      "total_supply": 18446744.07370955
    },
    {
      "symbol": "USDE",
      "name": "Ethena USDe",
      "price": 0.999555,
      "change24h": 0.02455,
      "marketCap": 5922456280,
      "volume24h": 79021213,
      "ath": 1.034,
      "ath_change_percentage": -3.30281,
      "sparkScore": 41,
      "circulating_supply": 5925000376.557542,
      "total_supply": 5925000376.557542
    },
    {
      "symbol": "CC",
      "name": "Canton",
      "price": 0.14481,
      "change24h": -1.99648,
      "marketCap": 5516678531,
      "volume24h": 7342099,
      "ath": 0.194152,
      "ath_change_percentage": -25.42224,
      "sparkScore": 30,
      "circulating_supply": 38074529849.07894,
      "total_supply": 38074529849.07894
    }
  ],
  "all_coins": [
    {
      "symbol": "BTC",
      "name": "Bitcoin",
      "price": 70325,
      "change24h": -1.00039,
      "marketCap": 1406776357920,
      "volume24h": 45835893457,
      "ath": 126080,
      "ath_change_percentage": -44.22192,
      "sparkScore": 55,
      "circulating_supply": 20003043.0,
      "total_supply": 20003043.0
    },
    {
      "symbol": "ETH",
      "name": "Ethereum",
      "price": 2144.92,
      "change24h": -2.19974,
      "marketCap": 258855171414,
      "volume24h": 24223220671,
      "ath": 4946.05,
      "ath_change_percentage": -56.63366,
      "sparkScore": 68,
      "circulating_supply": 120691801.1632979,
      "total_supply": 120691801.1632979
    },
    {
      "symbol": "USDT",
      "name": "Tether",
      "price": 1.0,
      "change24h": 0.01403,
      "marketCap": 184118402139,
      "volume24h": 76943301106,
      "ath": 1.32,
      "ath_change_percentage": -24.40882,
      "sparkScore": 62,
      "circulating_supply": 184092103149.706,
      "total_supply": 189559041966.2262
    },
    {
      "symbol": "XRP",
      "name": "XRP",
      "price": 1.45,
      "change24h": -0.72609,
      "marketCap": 88954959088,
      "volume24h": 2631447438,
      "ath": 3.65,
      "ath_change_percentage": -60.17012,
      "sparkScore": 50,
      "circulating_supply": 61227832454.0,
      "total_supply": 99985701766.0
    },
    {
      "symbol": "BNB",
      "name": "BNB",
      "price": 641.28,
      "change24h": -1.52748,
      "marketCap": 87446882976,
      "volume24h": 1082202936,
      "ath": 1369.99,
      "ath_change_percentage": -53.19095,
      "sparkScore": 51,
      "circulating_supply": 136357724.82,
      "total_supply": 136357724.82
    },
    {
      "symbol": "USDC",
      "name": "USDC",
      "price": 0.999908,
      "change24h": -0.00265,
      "marketCap": 79237307963,
      "volume24h": 6254423340,
      "ath": 1.043,
      "ath_change_percentage": -4.16955,
      "sparkScore": 57,
      "circulating_supply": 79241721014.62352,
      "total_supply": 79242103272.56729
    },
    {
      "symbol": "SOL",
      "name": "Solana",
      "price": 89.05,
      "change24h": -1.36067,
      "marketCap": 50949531738,
      "volume24h": 3550987332,
      "ath": 293.31,
      "ath_change_percentage": -69.63982,
      "sparkScore": 60,
      "circulating_supply": 571567565.2857559,
      "total_supply": 571567585.9824531
    },
    {
      "symbol": "TRX",
      "name": "TRON",
      "price": 0.303476,
      "change24h": -0.21076,
      "marketCap": 28753181448,
      "volume24h": 539098070,
      "ath": 0.431288,
      "ath_change_percentage": -29.63502,
      "sparkScore": 45,
      "circulating_supply": 94751085019.1791,
      "total_supply": 94751265525.2406
    },
    {
      "symbol": "FIGR_HELOC",
      "name": "Figure Heloc",
      "price": 1.033,
      "change24h": 1.03121,
      "marketCap": 16364027615,
      "volume24h": 30110241,
      "ath": 1.049,
      "ath_change_percentage": -1.55054,
      "sparkScore": 39,
      "circulating_supply": 15843541913.347,
      "total_supply": 15843541913.347
    },
    {
      "symbol": "DOGE",
      "name": "Dogecoin",
      "price": 0.093536,
      "change24h": -1.65593,
      "marketCap": 14357853955,
      "volume24h": 943990917,
      "ath": 0.731578,
      "ath_change_percentage": -87.21452,
      "sparkScore": 55,
      "circulating_supply": 153478026383.7052,
      "total_supply": 153478756383.7052
    },
    {
      "symbol": "WBT",
      "name": "WhiteBIT Coin",
      "price": 55.54,
      "change24h": -2.59681,
      "marketCap": 11853191306,
      "volume24h": 77011232,
      "ath": 64.11,
      "ath_change_percentage": -13.33276,
      "sparkScore": 47,
      "circulating_supply": 213418274.0,
      "total_supply": 319918274.0
    },
    {
      "symbol": "USDS",
      "name": "USDS",
      "price": 0.999975,
      "change24h": 0.00916,
      "marketCap": 11460579431,
      "volume24h": 11556756,
      "ath": 1.057,
      "ath_change_percentage": -5.37022,
      "sparkScore": 37,
      "circulating_supply": 11460873503.22658,
      "total_supply": 11460873503.22658
    },
    {
      "symbol": "ADA",
      "name": "Cardano",
      "price": 0.267157,
      "change24h": -2.33154,
      "marketCap": 9845310690,
      "volume24h": 428424077,
      "ath": 3.09,
      "ath_change_percentage": -91.34548,
      "sparkScore": 48,
      "circulating_supply": 36846946339.91323,
      "total_supply": 45000000000.0
    },
    {
      "symbol": "HYPE",
      "name": "Hyperliquid",
      "price": 39.18,
      "change24h": -7.4432,
      "marketCap": 9342787522,
      "volume24h": 438605491,
      "ath": 59.3,
      "ath_change_percentage": -33.93501,
      "sparkScore": 54,
      "circulating_supply": 238385315.9541414,
      "total_supply": 962274028.9541414
    },
    {
      "symbol": "BCH",
      "name": "Bitcoin Cash",
      "price": 455.44,
      "change24h": -0.32567,
      "marketCap": 9114211573,
      "volume24h": 199817086,
      "ath": 3785.82,
      "ath_change_percentage": -87.96982,
      "sparkScore": 50,
      "circulating_supply": 20009618.64665078,
      "total_supply": 20009899.89665078
    },
    {
      "symbol": "LEO",
      "name": "LEO Token",
      "price": 9.17,
      "change24h": 1.10423,
      "marketCap": 8442927149,
      "volume24h": 1297364,
      "ath": 10.14,
      "ath_change_percentage": -9.53238,
      "sparkScore": 32,
      "circulating_supply": 921076216.9,
      "total_supply": 985239504.0
    },
    {
      "symbol": "LINK",
      "name": "Chainlink",
      "price": 9.07,
      "change24h": -1.53608,
      "marketCap": 6426622194,
      "volume24h": 389547793,
      "ath": 52.7,
      "ath_change_percentage": -82.77955,
      "sparkScore": 53,
      "circulating_supply": 708099970.4525867,
      "total_supply": 1000000000.0
    },
    {
      "symbol": "XMR",
      "name": "Monero",
      "price": 339.88,
      "change24h": -1.30329,
      "marketCap": 6269667808,
      "volume24h": 77221341,
      "ath": 797.73,
      "ath_change_percentage": -57.39444,
      "sparkScore": 48,
      "circulating_supply": 18446744.07370955,
      "total_supply": 18446744.07370955
    },
    {
      "symbol": "USDE",
      "name": "Ethena USDe",
      "price": 0.999555,
      "change24h": 0.02455,
      "marketCap": 5922456280,
      "volume24h": 79021213,
      "ath": 1.034,
      "ath_change_percentage": -3.30281,
      "sparkScore": 41,
      "circulating_supply": 5925000376.557542,
      "total_supply": 5925000376.557542
    },
    {
      "symbol": "CC",
      "name": "Canton",
      "price": 0.14481,
      "change24h": -1.99648,
      "marketCap": 5516678531,
      "volume24h": 7342099,
      "ath": 0.194152,
      "ath_change_percentage": -25.42224,
      "sparkScore": 30,
      "circulating_supply": 38074529849.07894,
      "total_supply": 38074529849.07894
    },
    {
      "symbol": "XLM",
      "name": "Stellar",
      "price": 0.165475,
      "change24h": -2.47011,
      "marketCap": 5463042873,
      "volume24h": 86853354,
      "ath": 0.875563,
      "ath_change_percentage": -81.08462,
      "sparkScore": 42,
      "circulating_supply": 33010193125.68989,
      "total_supply": 50001786883.65895
    },
    {
      "symbol": "USD1",
      "name": "USD1",
      "price": 0.999689,
      "change24h": 0.05469,
      "marketCap": 4453684542,
      "volume24h": 1650460270,
      "ath": 1.025,
      "ath_change_percentage": -2.50964,
      "sparkScore": 59,
      "circulating_supply": 4457753170.103694,
      "total_supply": 4457753170.103694
    },
    {
      "symbol": "DAI",
      "name": "Dai",
      "price": 0.999928,
      "change24h": 0.0173,
      "marketCap": 4308436325,
      "volume24h": 153198256,
      "ath": 1.22,
      "ath_change_percentage": -17.97001,
      "sparkScore": 46,
      "circulating_supply": 4308788535.11576,
      "total_supply": 4308788535.11576
    },
    {
      "symbol": "LTC",
      "name": "Litecoin",
      "price": 55.65,
      "change24h": -0.96678,
      "marketCap": 4282853816,
      "volume24h": 352420572,
      "ath": 410.26,
      "ath_change_percentage": -86.4338,
      "sparkScore": 59,
      "circulating_supply": 76966739.48347135,
      "total_supply": 76967608.23347135
    },
    {
      "symbol": "RAIN",
      "name": "Rain",
      "price": 0.00883963,
      "change24h": -1.62037,
      "marketCap": 4229426165,
      "volume24h": 21954799,
      "ath": 0.01090099,
      "ath_change_percentage": -18.85382,
      "sparkScore": 35,
      "circulating_supply": 478092691532.2214,
      "total_supply": 1149921963040.423
    },
    {
      "symbol": "AVAX",
      "name": "Avalanche",
      "price": 9.5,
      "change24h": -1.95386,
      "marketCap": 4101314887,
      "volume24h": 251699430,
      "ath": 144.96,
      "ath_change_percentage": -93.43716,
      "sparkScore": 53,
      "circulating_supply": 431771961.1772119,
      "total_supply": 463441061.1772119
    },
    {
      "symbol": "PYUSD",
      "name": "PayPal USD",
      "price": 1.0,
      "change24h": 0.01386,
      "marketCap": 4073932956,
      "volume24h": 68350130,
      "ath": 1.021,
      "ath_change_percentage": -2.02723,
      "sparkScore": 42,
      "circulating_supply": 4074021977.762924,
      "total_supply": 4074128389.603366
    },
    {
      "symbol": "HBAR",
      "name": "Hedera",
      "price": 0.09315,
      "change24h": -2.52505,
      "marketCap": 4034354348,
      "volume24h": 80429814,
      "ath": 0.569229,
      "ath_change_percentage": -83.61581,
      "sparkScore": 43,
      "circulating_supply": 43303446051.95932,
      "total_supply": 50000000000.0
    },
    {
      "symbol": "ZEC",
      "name": "Zcash",
      "price": 239.1,
      "change24h": -4.00968,
      "marketCap": 3972657505,
      "volume24h": 363010755,
      "ath": 3191.93,
      "ath_change_percentage": -92.50914,
      "sparkScore": 65,
      "circulating_supply": 16611853.2905448,
      "total_supply": 16612025.1655448
    },
    {
      "symbol": "SUI",
      "name": "Sui",
      "price": 0.959663,
      "change24h": -2.58879,
      "marketCap": 3743752218,
      "volume24h": 367190948,
      "ath": 5.35,
      "ath_change_percentage": -82.05086,
      "sparkScore": 59,
      "circulating_supply": 3899984688.415443,
      "total_supply": 10000000000.0
    },
    {
      "symbol": "SHIB",
      "name": "Shiba Inu",
      "price": 5.77e-06,
      "change24h": -0.45734,
      "marketCap": 3401180055,
      "volume24h": 125941784,
      "ath": 8.616e-05,
      "ath_change_percentage": -93.30149,
      "sparkScore": 46,
      "circulating_supply": 589243650032071.6,
      "total_supply": 589500198090109.2
    },
    {
      "symbol": "CRO",
      "name": "Cronos",
      "price": 0.075235,
      "change24h": -2.05045,
      "marketCap": 3183225961,
      "volume24h": 10393685,
      "ath": 0.891544,
      "ath_change_percentage": -91.55421,
      "sparkScore": 35,
      "circulating_supply": 42283759757.23901,
      "total_supply": 98483712630.18297
    },
    {
      "symbol": "M",
      "name": "MemeCore",
      "price": 1.8,
      "change24h": -5.73559,
      "marketCap": 3142440728,
      "volume24h": 12604935,
      "ath": 2.96,
      "ath_change_percentage": -39.17956,
      "sparkScore": 38,
      "circulating_supply": 1747940802.223463,
      "total_supply": 5347940801.782739
    },
    {
      "symbol": "TON",
      "name": "Toncoin",
      "price": 1.23,
      "change24h": -5.46842,
      "marketCap": 3024735214,
      "volume24h": 97108261,
      "ath": 8.25,
      "ath_change_percentage": -85.07424,
      "sparkScore": 48,
      "circulating_supply": 2459352226.293346,
      "total_supply": 5157232841.708404
    },
    {
      "symbol": "XAUT",
      "name": "Tether Gold",
      "price": 4663.02,
      "change24h": -2.97676,
      "marketCap": 2632353883,
      "volume24h": 973880147,
      "ath": 5504.62,
      "ath_change_percentage": -15.2914,
      "sparkScore": 66,
      "circulating_supply": 564598.641692,
      "total_supply": 712747.089
    },
    {
      "symbol": "WLFI",
      "name": "World Liberty Financial",
      "price": 0.09345,
      "change24h": -4.35888,
      "marketCap": 2585825266,
      "volume24h": 67765955,
      "ath": 0.331336,
      "ath_change_percentage": -71.79603,
      "sparkScore": 45,
      "circulating_supply": 27661968598.0,
      "total_supply": 100000000000.0
    },
    {
      "symbol": "TAO",
      "name": "Bittensor",
      "price": 266.23,
      "change24h": -0.32197,
      "marketCap": 2551749046,
      "volume24h": 335923733,
      "ath": 757.6,
      "ath_change_percentage": -64.97601,
      "sparkScore": 66,
      "circulating_supply": 9597491.0,
      "total_supply": 21000000.0
    },
    {
      "symbol": "DOT",
      "name": "Polkadot",
      "price": 1.52,
      "change24h": -2.64393,
      "marketCap": 2543940700,
      "volume24h": 190349031,
      "ath": 54.98,
      "ath_change_percentage": -97.22887,
      "sparkScore": 56,
      "circulating_supply": 1675225788.807275,
      "total_supply": 1675225788.807275
    },
    {
      "symbol": "MNT",
      "name": "Mantle",
      "price": 0.748467,
      "change24h": -2.91229,
      "marketCap": 2455845064,
      "volume24h": 46528636,
      "ath": 2.86,
      "ath_change_percentage": -73.74823,
      "sparkScore": 38,
      "circulating_supply": 3277944055.53684,
      "total_supply": 6219316794.889999
    },
    {
      "symbol": "USYC",
      "name": "Circle USYC",
      "price": 1.12,
      "change24h": 0.00927,
      "marketCap": 2410632243,
      "volume24h": 223739,
      "ath": 1.12,
      "ath_change_percentage": -0.08073,
      "sparkScore": 29,
      "circulating_supply": 2154860884.911417,
      "total_supply": 2154860884.911417
    },
    {
      "symbol": "PAXG",
      "name": "PAX Gold",
      "price": 4670.92,
      "change24h": -3.05389,
      "marketCap": 2342999967,
      "volume24h": 721778682,
      "ath": 5619.09,
      "ath_change_percentage": -16.82868,
      "sparkScore": 66,
      "circulating_supply": 501552.248,
      "total_supply": 501552.248
    },
    {
      "symbol": "UNI",
      "name": "Uniswap",
      "price": 3.57,
      "change24h": -3.1245,
      "marketCap": 2263521432,
      "volume24h": 224537945,
      "ath": 44.92,
      "ath_change_percentage": -92.03232,
      "sparkScore": 61,
      "circulating_supply": 633561603.6037512,
      "total_supply": 897998420.0366304
    },
    {
      "symbol": "BUIDL",
      "name": "BlackRock USD Institutional Digital Liquidity Fund",
      "price": 1.0,
      "change24h": 0.0,
      "marketCap": 2012475046,
      "volume24h": 0.0,
      "ath": 1.0,
      "ath_change_percentage": 0.0,
      "sparkScore": 24,
      "circulating_supply": 2012475046.050449,
      "total_supply": 2012475046.050449
    },
    {
      "symbol": "OKB",
      "name": "OKB",
      "price": 88.71,
      "change24h": -3.53921,
      "marketCap": 1863577879,
      "volume24h": 22839894,
      "ath": 228.74,
      "ath_change_percentage": -61.17532,
      "sparkScore": 41,
      "circulating_supply": 21000000.0,
      "total_supply": 21000000.0
    },
    {
      "symbol": "USDG",
      "name": "Global Dollar",
      "price": 0.999939,
      "change24h": 0.01043,
      "marketCap": 1776273690,
      "volume24h": 22181111,
      "ath": 1.65,
      "ath_change_percentage": -39.56584,
      "sparkScore": 36,
      "circulating_supply": 1776618666.310112,
      "total_supply": 1776618666.310112
    },
    {
      "symbol": "USDF",
      "name": "Falcon USD",
      "price": 0.998137,
      "change24h": 0.0407,
      "marketCap": 1749059777,
      "volume24h": 2702815,
      "ath": 1.075,
      "ath_change_percentage": -7.09549,
      "sparkScore": 30,
      "circulating_supply": 1752557423.525555,
      "total_supply": 1752557423.525555
    },
    {
      "symbol": "PI",
      "name": "Pi Network",
      "price": 0.176579,
      "change24h": 2.07843,
      "marketCap": 1733541135,
      "volume24h": 26601069,
      "ath": 2.99,
      "ath_change_percentage": -94.07077,
      "sparkScore": 37,
      "circulating_supply": 9803765409.228682,
      "total_supply": 15082716014.19797
    },
    {
      "symbol": "NEAR",
      "name": "NEAR Protocol",
      "price": 1.33,
      "change24h": -4.43613,
      "marketCap": 1716787913,
      "volume24h": 173907243,
      "ath": 20.44,
      "ath_change_percentage": -93.48301,
      "sparkScore": 62,
      "circulating_supply": 1290628230.0,
      "total_supply": 1290628275.0
    },
    {
      "symbol": "AAVE",
      "name": "Aave",
      "price": 111.77,
      "change24h": -2.8215,
      "marketCap": 1697849572,
      "volume24h": 371813222,
      "ath": 661.69,
      "ath_change_percentage": -83.06429,
      "sparkScore": 66,
      "circulating_supply": 15184069.784566047,
      "total_supply": 16000000.0
    },
    {
      "symbol": "ASTER",
      "name": "Aster",
      "price": 0.690369,
      "change24h": -0.6037,
      "marketCap": 1697520557,
      "volume24h": 183330603,
      "ath": 2.41,
      "ath_change_percentage": -71.33896,
      "sparkScore": 59,
      "circulating_supply": 2455859719.12999,
      "total_supply": 7822529124.604758
    },
    {
      "symbol": "SKY",
      "name": "Sky",
      "price": 0.071403,
      "change24h": 0.06694,
      "marketCap": 1647495395,
      "volume24h": 13568971,
      "ath": 0.100535,
      "ath_change_percentage": -28.93114,
      "sparkScore": 35,
      "circulating_supply": 23071806970.27323,
      "total_supply": 23462665147.36596
    },
    {
      "symbol": "HTX",
      "name": "HTX DAO",
      "price": 1.67e-06,
      "change24h": -0.16292,
      "marketCap": 1529938261,
      "volume24h": 18058409,
      "ath": 3.75e-06,
      "ath_change_percentage": -55.50391,
      "sparkScore": 36,
      "circulating_supply": 916533066327098.8,
      "total_supply": 916533066327098.8
    },
    {
      "symbol": "RLUSD",
      "name": "Ripple USD",
      "price": 0.999792,
      "change24h": -0.01713,
      "marketCap": 1525574183,
      "volume24h": 103379848,
      "ath": 1.073,
      "ath_change_percentage": -6.79426,
      "sparkScore": 52,
      "circulating_supply": 1525616168.127284,
      "total_supply": 1525616168.127284
    },
    {
      "symbol": "BGB",
      "name": "Bitget Token",
      "price": 2.13,
      "change24h": -1.29344,
      "marketCap": 1487744254,
      "volume24h": 14934423,
      "ath": 8.45,
      "ath_change_percentage": -74.83866,
      "sparkScore": 38,
      "circulating_supply": 699992035.9787906,
      "total_supply": 916931610.9787906
    },
    {
      "symbol": "PEPE",
      "name": "Pepe",
      "price": 3.41e-06,
      "change24h": -3.14741,
      "marketCap": 1433611630,
      "volume24h": 320393628,
      "ath": 2.803e-05,
      "ath_change_percentage": -87.84367,
      "sparkScore": 59,
      "circulating_supply": 420690000000000.0,
      "total_supply": 420690000000000.0
    },
    {
      "symbol": "ICP",
      "name": "Internet Computer",
      "price": 2.49,
      "change24h": -3.37742,
      "marketCap": 1370333408,
      "volume24h": 48234788,
      "ath": 700.65,
      "ath_change_percentage": -99.6444,
      "sparkScore": 43,
      "circulating_supply": 550491293.6333674,
      "total_supply": 550491293.6333674
    },
    {
      "symbol": "BFUSD",
      "name": "BFUSD",
      "price": 0.999397,
      "change24h": 0.00958,
      "marketCap": 1319072913,
      "volume24h": 2723246,
      "ath": 1.007,
      "ath_change_percentage": -0.75744,
      "sparkScore": 30,
      "circulating_supply": 1320000000.0,
      "total_supply": 1320000000.0
    },
    {
      "symbol": "ETC",
      "name": "Ethereum Classic",
      "price": 8.37,
      "change24h": -1.58634,
      "marketCap": 1303731656,
      "volume24h": 42902732,
      "ath": 167.09,
      "ath_change_percentage": -94.99399,
      "sparkScore": 42,
      "circulating_supply": 155966011.5955624,
      "total_supply": 155966011.5955624
    },
    {
      "symbol": "USDY",
      "name": "Ondo US Dollar Yield",
      "price": 1.11,
      "change24h": -1.0952,
      "marketCap": 1300733633,
      "volume24h": 1148497,
      "ath": 1.26,
      "ath_change_percentage": -10.99823,
      "sparkScore": 32,
      "circulating_supply": 1170556747.325068,
      "total_supply": 1170556747.325068
    },
    {
      "symbol": "ONDO",
      "name": "Ondo",
      "price": 0.258015,
      "change24h": -3.48554,
      "marketCap": 1256932043,
      "volume24h": 46570834,
      "ath": 2.14,
      "ath_change_percentage": -87.94411,
      "sparkScore": 42,
      "circulating_supply": 4869330647.0,
      "total_supply": 10000000000.0
    },
    {
      "symbol": "USTB",
      "name": "Superstate Short Duration U.S. Government Securities Fund (USTB)",
      "price": 11.02,
      "change24h": 0.00956,
      "marketCap": 1222054098,
      "volume24h": 0.0,
      "ath": 11.02,
      "ath_change_percentage": 0.0,
      "sparkScore": 28,
      "circulating_supply": 110849871.417349,
      "total_supply": 110849871.417349
    },
    {
      "symbol": "GT",
      "name": "Gate",
      "price": 6.77,
      "change24h": -2.83922,
      "marketCap": 1133103428,
      "volume24h": 3062129,
      "ath": 25.38,
      "ath_change_percentage": -73.37255,
      "sparkScore": 33,
      "circulating_supply": 115180573.04885802,
      "total_supply": 115180573.04885802
    },
    {
      "symbol": "PUMP",
      "name": "Pump.fun",
      "price": 0.00185868,
      "change24h": -5.01486,
      "marketCap": 1097934072,
      "volume24h": 80726566,
      "ath": 0.00881908,
      "ath_change_percentage": -78.9243,
      "sparkScore": 54,
      "circulating_supply": 590000000000.0,
      "total_supply": 999989182511.4219
    },
    {
      "symbol": "QNT",
      "name": "Quant",
      "price": 74.97,
      "change24h": 4.90408,
      "marketCap": 1090803541,
      "volume24h": 40210136,
      "ath": 427.42,
      "ath_change_percentage": -82.4614,
      "sparkScore": 46,
      "circulating_supply": 14544176.164081175,
      "total_supply": 14612493.0
    },
    {
      "symbol": "KCS",
      "name": "KuCoin",
      "price": 7.96,
      "change24h": -1.19513,
      "marketCap": 1052533951,
      "volume24h": 1668461,
      "ath": 28.83,
      "ath_change_percentage": -72.33782,
      "sparkScore": 32,
      "circulating_supply": 132155021.7355671,
      "total_supply": 142155021.7355671
    },
    {
      "symbol": "EUTBL",
      "name": "Spiko EU T-Bills Money Market Fund",
      "price": 1.22,
      "change24h": 1.17054,
      "marketCap": 1026020254,
      "volume24h": 0.0,
      "ath": 1.26,
      "ath_change_percentage": -3.66535,
      "sparkScore": 26,
      "circulating_supply": 844130793.49121,
      "total_supply": 844130793.49121
    },
    {
      "symbol": "POL",
      "name": "POL (ex-MATIC)",
      "price": 0.09553,
      "change24h": -1.57699,
      "marketCap": 1013914880,
      "volume24h": 43569277,
      "ath": 1.29,
      "ath_change_percentage": -92.57832,
      "sparkScore": 42,
      "circulating_supply": 10610558433.01956,
      "total_supply": 10610558433.01956
    },
    {
      "symbol": "KAS",
      "name": "Kaspa",
      "price": 0.03758189,
      "change24h": -2.71175,
      "marketCap": 1006557720,
      "volume24h": 39510262,
      "ath": 0.207411,
      "ath_change_percentage": -81.87459,
      "sparkScore": 42,
      "circulating_supply": 26777148610.50726,
      "total_supply": 27294598932.50496
    },
    {
      "symbol": "WLD",
      "name": "Worldcoin",
      "price": 0.333611,
      "change24h": -9.07931,
      "marketCap": 991471933,
      "volume24h": 176576982,
      "ath": 11.74,
      "ath_change_percentage": -97.15302,
      "sparkScore": 57,
      "circulating_supply": 2969586430.040101,
      "total_supply": 10000000000.0
    },
    {
      "symbol": "MORPHO",
      "name": "Morpho",
      "price": 1.77,
      "change24h": 1.29528,
      "marketCap": 972457021,
      "volume24h": 18390010,
      "ath": 4.17,
      "ath_change_percentage": -57.63459,
      "sparkScore": 36,
      "circulating_supply": 549905044.8090589,
      "total_supply": 1000000000.0
    },
    {
      "symbol": "ATOM",
      "name": "Cosmos Hub",
      "price": 1.84,
      "change24h": -3.43462,
      "marketCap": 916108453,
      "volume24h": 33523583,
      "ath": 43.84,
      "ath_change_percentage": -95.80745,
      "sparkScore": 40,
      "circulating_supply": 498909956.753183,
      "total_supply": 498909956.753183
    },
    {
      "symbol": "JTRSY",
      "name": "Janus Henderson Anemoy Treasury Fund",
      "price": 1.098,
      "change24h": 0.0062,
      "marketCap": 914611990,
      "volume24h": 0.0,
      "ath": 1.098,
      "ath_change_percentage": 0.0,
      "sparkScore": 22,
      "circulating_supply": 833268335.219541,
      "total_supply": 833268335.219541
    },
    {
      "symbol": "NEXO",
      "name": "NEXO",
      "price": 0.900321,
      "change24h": -0.59773,
      "marketCap": 900332502,
      "volume24h": 6927992,
      "ath": 4.07,
      "ath_change_percentage": -77.8322,
      "sparkScore": 27,
      "circulating_supply": 1000000000.0,
      "total_supply": 1000000000.0
    },
    {
      "symbol": "ENA",
      "name": "Ethena",
      "price": 0.103649,
      "change24h": -4.59838,
      "marketCap": 880602176,
      "volume24h": 83081648,
      "ath": 1.52,
      "ath_change_percentage": -93.16516,
      "sparkScore": 55,
      "circulating_supply": 8492187500.0,
      "total_supply": 15000000000.0
    },
    {
      "symbol": "RENDER",
      "name": "Render",
      "price": 1.68,
      "change24h": -3.06894,
      "marketCap": 870748987,
      "volume24h": 58807797,
      "ath": 13.53,
      "ath_change_percentage": -87.60625,
      "sparkScore": 51,
      "circulating_supply": 518743261.0140742,
      "total_supply": 533503434.2940742
    },
    {
      "symbol": "USDTB",
      "name": "USDtb",
      "price": 0.999273,
      "change24h": -0.00923,
      "marketCap": 827152489,
      "volume24h": 672218,
      "ath": 1.057,
      "ath_change_percentage": -5.46327,
      "sparkScore": 23,
      "circulating_supply": 827749079.8061825,
      "total_supply": 827749079.8061825
    },
    {
      "symbol": "HASH",
      "name": "Provenance Blockchain",
      "price": 0.01445615,
      "change24h": 13.58903,
      "marketCap": 807620737,
      "volume24h": 112311,
      "ath": 0.060147,
      "ath_change_percentage": -75.96527,
      "sparkScore": 26,
      "circulating_supply": 55866936903.0,
      "total_supply": 100000000000.0
    },
    {
      "symbol": "ALGO",
      "name": "Algorand",
      "price": 0.089161,
      "change24h": -1.36652,
      "marketCap": 792949591,
      "volume24h": 31724470,
      "ath": 3.56,
      "ath_change_percentage": -97.49188,
      "sparkScore": 38,
      "circulating_supply": 8891136520.603544,
      "total_supply": 8891174055.14366
    },
    {
      "symbol": "TRUMP",
      "name": "Official Trump",
      "price": 3.37,
      "change24h": -3.08092,
      "marketCap": 784011343,
      "volume24h": 140557116,
      "ath": 73.43,
      "ath_change_percentage": -95.41056,
      "sparkScore": 57,
      "circulating_supply": 232498807.465716,
      "total_supply": 1000000000.0
    },
    {
      "symbol": "APT",
      "name": "Aptos",
      "price": 0.94217,
      "change24h": -4.0218,
      "marketCap": 748397485,
      "volume24h": 84582221,
      "ath": 19.92,
      "ath_change_percentage": -95.2565,
      "sparkScore": 56,
      "circulating_supply": 793544139.2981135,
      "total_supply": 1199843117.416494
    },
    {
      "symbol": "USDD",
      "name": "USDD",
      "price": 0.999533,
      "change24h": -0.04004,
      "marketCap": 747549164,
      "volume24h": 2104785,
      "ath": 1.052,
      "ath_change_percentage": -4.92083,
      "sparkScore": 26,
      "circulating_supply": 747806138.53,
      "total_supply": 747806138.67
    },
    {
      "symbol": "NIGHT",
      "name": "Midnight",
      "price": 0.04419001,
      "change24h": -5.88905,
      "marketCap": 733903651,
      "volume24h": 287628149,
      "ath": 0.118529,
      "ath_change_percentage": -62.68449,
      "sparkScore": 56,
      "circulating_supply": 16607399400.63495,
      "total_supply": 24000000000.0
    },
    {
      "symbol": "OUSG",
      "name": "OUSG",
      "price": 114.64,
      "change24h": 0.00915,
      "marketCap": 719674231,
      "volume24h": 0.0,
      "ath": 114.64,
      "ath_change_percentage": 0.0,
      "sparkScore": 27,
      "circulating_supply": 6277606.877031929,
      "total_supply": 6277606.877031929
    },
    {
      "symbol": "FLR",
      "name": "Flare",
      "price": 0.00833929,
      "change24h": -0.89932,
      "marketCap": 711249251,
      "volume24h": 3345412,
      "ath": 0.150073,
      "ath_change_percentage": -94.443,
      "sparkScore": 27,
      "circulating_supply": 85279931791.87515,
      "total_supply": 105252614433.4361
    },
    {
      "symbol": "FIL",
      "name": "Filecoin",
      "price": 0.889575,
      "change24h": -3.79835,
      "marketCap": 678465871,
      "volume24h": 65661397,
      "ath": 236.84,
      "ath_change_percentage": -99.6237,
      "sparkScore": 55,
      "circulating_supply": 762435720.0,
      "total_supply": 1957975648.0
    },
    {
      "symbol": "VET",
      "name": "VeChain",
      "price": 0.00724719,
      "change24h": -0.51258,
      "marketCap": 623218591,
      "volume24h": 12650337,
      "ath": 0.280991,
      "ath_change_percentage": -97.41852,
      "sparkScore": 34,
      "circulating_supply": 85985041177.0,
      "total_supply": 85985041177.0
    },
    {
      "symbol": "XDC",
      "name": "XDC Network",
      "price": 0.03195498,
      "change24h": 0.61162,
      "marketCap": 619241472,
      "volume24h": 18697103,
      "ath": 0.192754,
      "ath_change_percentage": -83.42875,
      "sparkScore": 36,
      "circulating_supply": 19380993246.87,
      "total_supply": 38057686866.0
    },
    {
      "symbol": "BDX",
      "name": "Beldex",
      "price": 0.080751,
      "change24h": -1.47894,
      "marketCap": 614187097,
      "volume24h": 12938542,
      "ath": 0.450785,
      "ath_change_percentage": -82.08548,
      "sparkScore": 34,
      "circulating_supply": 7606345820.420332,
      "total_supply": 9936645682.938492
    },
    {
      "symbol": "ARB",
      "name": "Arbitrum",
      "price": 0.099162,
      "change24h": -3.57464,
      "marketCap": 599238637,
      "volume24h": 50155947,
      "ath": 2.39,
      "ath_change_percentage": -95.84619,
      "sparkScore": 52,
      "circulating_supply": 6040824145.0,
      "total_supply": 10000000000.0
    },
    {
      "symbol": "GHO",
      "name": "GHO",
      "price": 1.0,
      "change24h": 0.02234,
      "marketCap": 583966439,
      "volume24h": 2977820,
      "ath": 1.03,
      "ath_change_percentage": -2.8937,
      "sparkScore": 27,
      "circulating_supply": 584000000.0,
      "total_supply": 584000000.0
    },
    {
      "symbol": "STABLE",
      "name": "\u200b\u200bStable",
      "price": 0.02757069,
      "change24h": 1.45577,
      "marketCap": 578611277,
      "volume24h": 18972690,
      "ath": 0.0388874,
      "ath_change_percentage": -29.23995,
      "sparkScore": 36,
      "circulating_supply": 21019658779.0,
      "total_supply": 100000000000.0
    },
    {
      "symbol": "SIREN",
      "name": "Siren",
      "price": 0.787768,
      "change24h": -11.64668,
      "marketCap": 573728431,
      "volume24h": 26059604,
      "ath": 0.965391,
      "ath_change_percentage": -18.22877,
      "sparkScore": 41,
      "circulating_supply": 728213818.6854393,
      "total_supply": 728213818.6854393
    },
    {
      "symbol": "YLDS",
      "name": "YLDS",
      "price": 0.999998,
      "change24h": 0.01575,
      "marketCap": 570563749,
      "volume24h": 7699573,
      "ath": 1.001,
      "ath_change_percentage": -0.10861,
      "sparkScore": 28,
      "circulating_supply": 570565015.56,
      "total_supply": 570565015.56
    },
    {
      "symbol": "JUP",
      "name": "Jupiter",
      "price": 0.160124,
      "change24h": -2.08827,
      "marketCap": 560529806,
      "volume24h": 18276019,
      "ath": 2.0,
      "ath_change_percentage": -91.98642,
      "sparkScore": 37,
      "circulating_supply": 3497363517.1,
      "total_supply": 6863982659.521815
    },
    {
      "symbol": "USD0",
      "name": "Usual USD",
      "price": 0.995557,
      "change24h": -0.27265,
      "marketCap": 560321210,
      "volume24h": 75506,
      "ath": 1.33,
      "ath_change_percentage": -24.83127,
      "sparkScore": 20,
      "circulating_supply": 562441878.8800157,
      "total_supply": 562441878.8800157
    },
    {
      "symbol": "BONK",
      "name": "Bonk",
      "price": 5.96e-06,
      "change24h": -3.13184,
      "marketCap": 525176028,
      "volume24h": 52711751,
      "ath": 5.825e-05,
      "ath_change_percentage": -89.74353,
      "sparkScore": 55,
      "circulating_supply": 87994756326074.88,
      "total_supply": 87994756326075.17
    },
    {
      "symbol": "ZRO",
      "name": "LayerZero",
      "price": 2.08,
      "change24h": -3.39041,
      "marketCap": 520481265,
      "volume24h": 72341929,
      "ath": 7.47,
      "ath_change_percentage": -72.11217,
      "sparkScore": 57,
      "circulating_supply": 249858416.45502064,
      "total_supply": 1000000000.0
    },
    {
      "symbol": "JST",
      "name": "JUST",
      "price": 0.058998,
      "change24h": 1.84253,
      "marketCap": 519913451,
      "volume24h": 29964311,
      "ath": 0.193254,
      "ath_change_percentage": -69.48435,
      "sparkScore": 41,
      "circulating_supply": 8815108920.581306,
      "total_supply": 8815108920.581306
    },
    {
      "symbol": "TUSD",
      "name": "TrueUSD",
      "price": 0.99972,
      "change24h": -0.00183,
      "marketCap": 494204421,
      "volume24h": 6625904,
      "ath": 1.62,
      "ath_change_percentage": -38.25412,
      "sparkScore": 28,
      "circulating_supply": 494515083.0,
      "total_supply": 494515083.0
    },
    {
      "symbol": "FET",
      "name": "Artificial Superintelligence Alliance",
      "price": 0.212281,
      "change24h": -3.71507,
      "marketCap": 479513702,
      "volume24h": 102742700,
      "ath": 3.45,
      "ath_change_percentage": -93.86443,
      "sparkScore": 55,
      "circulating_supply": 2260092822.776148,
      "total_supply": 2714384546.672
    }
  ],
  "new_coins": [
    {
      "symbol": "SIREN",
      "name": "Siren",
      "price": 0.787768,
      "change24h": -11.64668,
      "marketCap": 573728431,
      "volume24h": 26059604,
      "ath": 0.965391,
      "ath_change_percentage": -18.22877,
      "sparkScore": 41,
      "circulating_supply": 728213818.6854393,
      "total_supply": 728213818.6854393,
      "new_score": 86.42970519210527,
      "listed_since": "today",
      "potential": "high"
    },
    {
      "symbol": "RLUSD",
      "name": "Ripple USD",
      "price": 0.999792,
      "change24h": -0.01713,
      "marketCap": 1525574183,
      "volume24h": 103379848,
      "ath": 1.073,
      "ath_change_percentage": -6.79426,
      "sparkScore": 52,
      "circulating_supply": 1525616168.127284,
      "total_supply": 1525616168.127284,
      "new_score": 85.99852192494372,
      "listed_since": "today",
      "potential": "high"
    },
    {
      "symbol": "FET",
      "name": "Artificial Superintelligence Alliance",
      "price": 0.212281,
      "change24h": -3.71507,
      "marketCap": 479513702,
      "volume24h": 102742700,
      "ath": 3.45,
      "ath_change_percentage": -93.86443,
      "sparkScore": 55,
      "circulating_supply": 2260092822.776148,
      "total_supply": 2714384546.672,
      "new_score": 84.57742282501692,
      "listed_since": "today",
      "potential": "high"
    },
    {
      "symbol": "USD1",
      "name": "USD1",
      "price": 0.999689,
      "change24h": 0.05469,
      "marketCap": 4453684542,
      "volume24h": 1650460270,
      "ath": 1.025,
      "ath_change_percentage": -2.50964,
      "sparkScore": 59,
      "circulating_supply": 4457753170.103694,
      "total_supply": 4457753170.103694,
      "new_score": 83.6630639505954,
      "listed_since": "today",
      "potential": "high"
    },
    {
      "symbol": "PUMP",
      "name": "Pump.fun",
      "price": 0.00185868,
      "change24h": -5.01486,
      "marketCap": 1097934072,
      "volume24h": 80726566,
      "ath": 0.00881908,
      "ath_change_percentage": -78.9243,
      "sparkScore": 54,
      "circulating_supply": 590000000000.0,
      "total_supply": 999989182511.4219,
      "new_score": 81.95781415597929,
      "listed_since": "today",
      "potential": "high"
    }
  ],
  "total_coins": 100
}