{
  "timestamp": "2026-03-01T09:08:57.338807",
  "market_summary": {
    "total_market_cap": 2318800285856,
    "total_volume_24h": 181314600438.92,
    "total_coins_tracked": 100,
    "market_cap_change_24h": -0.56,
    "volume_change_24h": 0.0,
    "timestamp": "2026-03-01T09:08:57.338322"
  },
  "trending_coins": [
    {
      "symbol": "BTC",
      "name": "Bitcoin",
      "price": 66549,
      "change24h": 4.73809,
      "marketCap": 1331528465504,
      "volume24h": 47498361011,
      "ath": 126080,
      "ath_change_percentage": -47.21644,
      "sparkScore": 57,
      "circulating_supply": 19996312.0,
      "total_supply": 19996312.0
    },
    {
      "symbol": "ETH",
      "name": "Ethereum",
      "price": 1986.49,
      "change24h": 7.21012,
      "marketCap": 239920949027,
      "volume24h": 24210992799,
      "ath": 4946.05,
      "ath_change_percentage": -59.83687,
      "sparkScore": 70,
      "circulating_supply": 120692230.1356825,
      "total_supply": 120692230.1356825
    },
    {
      "symbol": "USDT",
      "name": "Tether",
      "price": 1.0,
      "change24h": 0.01398,
      "marketCap": 183658838860,
      "volume24h": 79500419002,
      "ath": 1.32,
      "ath_change_percentage": -24.41633,
      "sparkScore": 62,
      "circulating_supply": 183633868265.3761,
      "total_supply": 189100805662.9562
    },
    {
      "symbol": "BNB",
      "name": "BNB",
      "price": 621.28,
      "change24h": 5.31855,
      "marketCap": 84794704710,
      "volume24h": 1316268169,
      "ath": 1369.99,
      "ath_change_percentage": -54.65064,
      "sparkScore": 53,
      "circulating_supply": 136358742.0799999,
      "total_supply": 136358742.0799999
    },
    {
      "symbol": "XRP",
      "name": "XRP",
      "price": 1.38,
      "change24h": 7.35324,
      "marketCap": 84475824158,
      "volume24h": 4143634868,
      "ath": 3.65,
      "ath_change_percentage": -62.10743,
      "sparkScore": 55,
      "circulating_supply": 61090376977.0,
      "total_supply": 99985708785.0
    },
    {
      "symbol": "USDC",
      "name": "USDC",
      "price": 0.999905,
      "change24h": -0.00999,
      "marketCap": 75191180868,
      "volume24h": 3842936434,
      "ath": 1.17,
      "ath_change_percentage": -14.72925,
      "sparkScore": 52,
      "circulating_supply": 75197649839.2617,
      "total_supply": 75197729025.53967
    },
    {
      "symbol": "SOL",
      "name": "Solana",
      "price": 85.31,
      "change24h": 9.17563,
      "marketCap": 48605929584,
      "volume24h": 5546580414,
      "ath": 293.31,
      "ath_change_percentage": -70.91603,
      "sparkScore": 68,
      "circulating_supply": 569526077.0130299,
      "total_supply": 621330553.2493796
    },
    {
      "symbol": "TRX",
      "name": "TRON",
      "price": 0.281406,
      "change24h": 0.83543,
      "marketCap": 26663513049,
      "volume24h": 456220579,
      "ath": 0.431288,
      "ath_change_percentage": -34.75235,
      "sparkScore": 45,
      "circulating_supply": 94739563090.469,
      "total_supply": 94740733293.1299
    },
    {
      "symbol": "FIGR_HELOC",
      "name": "Figure Heloc",
      "price": 1.029,
      "change24h": -1.84536,
      "marketCap": 15913674381,
      "volume24h": 286520,
      "ath": 1.37,
      "ath_change_percentage": -24.86805,
      "sparkScore": 32,
      "circulating_supply": 15465041266.147,
      "total_supply": 15465041266.147
    },
    {
      "symbol": "DOGE",
      "name": "Dogecoin",
      "price": 0.093893,
      "change24h": 5.79847,
      "marketCap": 15866646775,
      "volume24h": 1545614497,
      "ath": 0.731578,
      "ath_change_percentage": -87.16566,
      "sparkScore": 62,
      "circulating_supply": 168909873126.579,
      "total_supply": 168938473126.5791
    },
    {
      "symbol": "WBT",
      "name": "WhiteBIT Coin",
      "price": 49.43,
      "change24h": 3.77698,
      "marketCap": 10553493110,
      "volume24h": 52420550,
      "ath": 64.11,
      "ath_change_percentage": -22.9058,
      "sparkScore": 47,
      "circulating_supply": 213544699.0,
      "total_supply": 320044699.0
    },
    {
      "symbol": "ADA",
      "name": "Cardano",
      "price": 0.279477,
      "change24h": 7.04244,
      "marketCap": 10302247764,
      "volume24h": 666237344,
      "ath": 3.09,
      "ath_change_percentage": -90.9464,
      "sparkScore": 56,
      "circulating_supply": 36820032120.64621,
      "total_supply": 45000000000.0
    },
    {
      "symbol": "USDS",
      "name": "USDS",
      "price": 0.999948,
      "change24h": 0.01533,
      "marketCap": 10099056556,
      "volume24h": 18862815,
      "ath": 1.057,
      "ath_change_percentage": -5.42603,
      "sparkScore": 37,
      "circulating_supply": 10099350239.50571,
      "total_supply": 10099350239.50571
    },
    {
      "symbol": "BCH",
      "name": "Bitcoin Cash",
      "price": 447.18,
      "change24h": 0.79919,
      "marketCap": 8947342849,
      "volume24h": 306627248,
      "ath": 3785.82,
      "ath_change_percentage": -88.18801,
      "sparkScore": 53,
      "circulating_supply": 20001199.89665078,
      "total_supply": 20001290.52165078
    },
    {
      "symbol": "LEO",
      "name": "LEO Token",
      "price": 8.96,
      "change24h": 1.46068,
      "marketCap": 8256325356,
      "volume24h": 641064,
      "ath": 10.14,
      "ath_change_percentage": -11.57572,
      "sparkScore": 29,
      "circulating_supply": 921252076.9,
      "total_supply": 985239504.0
    },
    {
      "symbol": "HYPE",
      "name": "Hyperliquid",
      "price": 30.64,
      "change24h": 13.97767,
      "marketCap": 7304555191,
      "volume24h": 348993203,
      "ath": 59.3,
      "ath_change_percentage": -48.33778,
      "sparkScore": 56,
      "circulating_supply": 238385315.9541414,
      "total_supply": 962274028.9541414
    },
    {
      "symbol": "XMR",
      "name": "Monero",
      "price": 343.33,
      "change24h": 1.79413,
      "marketCap": 6334058614,
      "volume24h": 88500208,
      "ath": 797.73,
      "ath_change_percentage": -56.96189,
      "sparkScore": 49,
      "circulating_supply": 18446744.07370955,
      "total_supply": 18446744.07370955
    },
    {
      "symbol": "LINK",
      "name": "Chainlink",
      "price": 8.91,
      "change24h": 7.59859,
      "marketCap": 6308631585,
      "volume24h": 490353096,
      "ath": 52.7,
      "ath_change_percentage": -83.09653,
      "sparkScore": 58,
      "circulating_supply": 708099970.4525867,
      "total_supply": 1000000000.0
    },
    {
      "symbol": "CC",
      "name": "Canton",
      "price": 0.165322,
      "change24h": 2.05601,
      "marketCap": 6265567841,
      "volume24h": 32366187,
      "ath": 0.194152,
      "ath_change_percentage": -15.02851,
      "sparkScore": 35,
      "circulating_supply": 37919381078.69655,
      "total_supply": 37919381078.69655
    },
    {
      "symbol": "USDE",
      "name": "Ethena USDe",
      "price": 0.99927,
      "change24h": 0.0087,
      "marketCap": 6028280182,
      "volume24h": 58637862,
      "ath": 1.034,
      "ath_change_percentage": -3.35406,
      "sparkScore": 40,
      "circulating_supply": 6032609839.413793,
      "total_supply": 6032609839.413793
    }
  ],
  "all_coins": [
    {
      "symbol": "BTC",
      "name": "Bitcoin",
      "price": 66549,
      "change24h": 4.73809,
      "marketCap": 1331528465504,
      "volume24h": 47498361011,
      "ath": 126080,
      "ath_change_percentage": -47.21644,
      "sparkScore": 57,
      "circulating_supply": 19996312.0,
      "total_supply": 19996312.0
    },
    {
      "symbol": "ETH",
      "name": "Ethereum",
      "price": 1986.49,
      "change24h": 7.21012,
      "marketCap": 239920949027,
      "volume24h": 24210992799,
      "ath": 4946.05,
      "ath_change_percentage": -59.83687,
      "sparkScore": 70,
      "circulating_supply": 120692230.1356825,
      "total_supply": 120692230.1356825
    },
    {
      "symbol": "USDT",
      "name": "Tether",
      "price": 1.0,
      "change24h": 0.01398,
      "marketCap": 183658838860,
      "volume24h": 79500419002,
      "ath": 1.32,
      "ath_change_percentage": -24.41633,
      "sparkScore": 62,
      "circulating_supply": 183633868265.3761,
      "total_supply": 189100805662.9562
    },
    {
      "symbol": "BNB",
      "name": "BNB",
      "price": 621.28,
      "change24h": 5.31855,
      "marketCap": 84794704710,
      "volume24h": 1316268169,
      "ath": 1369.99,
      "ath_change_percentage": -54.65064,
      "sparkScore": 53,
      "circulating_supply": 136358742.0799999,
      "total_supply": 136358742.0799999
    },
    {
      "symbol": "XRP",
      "name": "XRP",
      "price": 1.38,
      "change24h": 7.35324,
      "marketCap": 84475824158,
      "volume24h": 4143634868,
      "ath": 3.65,
      "ath_change_percentage": -62.10743,
      "sparkScore": 55,
      "circulating_supply": 61090376977.0,
      "total_supply": 99985708785.0
    },
    {
      "symbol": "USDC",
      "name": "USDC",
      "price": 0.999905,
      "change24h": -0.00999,
      "marketCap": 75191180868,
      "volume24h": 3842936434,
      "ath": 1.17,
      "ath_change_percentage": -14.72925,
      "sparkScore": 52,
      "circulating_supply": 75197649839.2617,
      "total_supply": 75197729025.53967
    },
    {
      "symbol": "SOL",
      "name": "Solana",
      "price": 85.31,
      "change24h": 9.17563,
      "marketCap": 48605929584,
      "volume24h": 5546580414,
      "ath": 293.31,
      "ath_change_percentage": -70.91603,
      "sparkScore": 68,
      "circulating_supply": 569526077.0130299,
      "total_supply": 621330553.2493796
    },
    {
      "symbol": "TRX",
      "name": "TRON",
      "price": 0.281406,
      "change24h": 0.83543,
      "marketCap": 26663513049,
      "volume24h": 456220579,
      "ath": 0.431288,
      "ath_change_percentage": -34.75235,
      "sparkScore": 45,
      "circulating_supply": 94739563090.469,
      "total_supply": 94740733293.1299
    },
    {
      "symbol": "FIGR_HELOC",
      "name": "Figure Heloc",
      "price": 1.029,
      "change24h": -1.84536,
      "marketCap": 15913674381,
      "volume24h": 286520,
      "ath": 1.37,
      "ath_change_percentage": -24.86805,
      "sparkScore": 32,
      "circulating_supply": 15465041266.147,
      "total_supply": 15465041266.147
    },
    {
      "symbol": "DOGE",
      "name": "Dogecoin",
      "price": 0.093893,
      "change24h": 5.79847,
      "marketCap": 15866646775,
      "volume24h": 1545614497,
      "ath": 0.731578,
      "ath_change_percentage": -87.16566,
      "sparkScore": 62,
      "circulating_supply": 168909873126.579,
      "total_supply": 168938473126.5791
    },
    {
      "symbol": "WBT",
      "name": "WhiteBIT Coin",
      "price": 49.43,
      "change24h": 3.77698,
      "marketCap": 10553493110,
      "volume24h": 52420550,
      "ath": 64.11,
      "ath_change_percentage": -22.9058,
      "sparkScore": 47,
      "circulating_supply": 213544699.0,
      "total_supply": 320044699.0
    },
    {
      "symbol": "ADA",
      "name": "Cardano",
      "price": 0.279477,
      "change24h": 7.04244,
      "marketCap": 10302247764,
      "volume24h": 666237344,
      "ath": 3.09,
      "ath_change_percentage": -90.9464,
      "sparkScore": 56,
      "circulating_supply": 36820032120.64621,
      "total_supply": 45000000000.0
    },
    {
      "symbol": "USDS",
      "name": "USDS",
      "price": 0.999948,
      "change24h": 0.01533,
      "marketCap": 10099056556,
      "volume24h": 18862815,
      "ath": 1.057,
      "ath_change_percentage": -5.42603,
      "sparkScore": 37,
      "circulating_supply": 10099350239.50571,
      "total_supply": 10099350239.50571
    },
    {
      "symbol": "BCH",
      "name": "Bitcoin Cash",
      "price": 447.18,
      "change24h": 0.79919,
      "marketCap": 8947342849,
      "volume24h": 306627248,
      "ath": 3785.82,
      "ath_change_percentage": -88.18801,
      "sparkScore": 53,
      "circulating_supply": 20001199.89665078,
      "total_supply": 20001290.52165078
    },
    {
      "symbol": "LEO",
      "name": "LEO Token",
      "price": 8.96,
      "change24h": 1.46068,
      "marketCap": 8256325356,
      "volume24h": 641064,
      "ath": 10.14,
      "ath_change_percentage": -11.57572,
      "sparkScore": 29,
      "circulating_supply": 921252076.9,
      "total_supply": 985239504.0
    },
    {
      "symbol": "HYPE",
      "name": "Hyperliquid",
      "price": 30.64,
      "change24h": 13.97767,
      "marketCap": 7304555191,
      "volume24h": 348993203,
      "ath": 59.3,
      "ath_change_percentage": -48.33778,
      "sparkScore": 56,
      "circulating_supply": 238385315.9541414,
      "total_supply": 962274028.9541414
    },
    {
      "symbol": "XMR",
      "name": "Monero",
      "price": 343.33,
      "change24h": 1.79413,
      "marketCap": 6334058614,
      "volume24h": 88500208,
      "ath": 797.73,
      "ath_change_percentage": -56.96189,
      "sparkScore": 49,
      "circulating_supply": 18446744.07370955,
      "total_supply": 18446744.07370955
    },
    {
      "symbol": "LINK",
      "name": "Chainlink",
      "price": 8.91,
      "change24h": 7.59859,
      "marketCap": 6308631585,
      "volume24h": 490353096,
      "ath": 52.7,
      "ath_change_percentage": -83.09653,
      "sparkScore": 58,
      "circulating_supply": 708099970.4525867,
      "total_supply": 1000000000.0
    },
    {
      "symbol": "CC",
      "name": "Canton",
      "price": 0.165322,
      "change24h": 2.05601,
      "marketCap": 6265567841,
      "volume24h": 32366187,
      "ath": 0.194152,
      "ath_change_percentage": -15.02851,
      "sparkScore": 35,
      "circulating_supply": 37919381078.69655,
      "total_supply": 37919381078.69655
    },
    {
      "symbol": "USDE",
      "name": "Ethena USDe",
      "price": 0.99927,
      "change24h": 0.0087,
      "marketCap": 6028280182,
      "volume24h": 58637862,
      "ath": 1.034,
      "ath_change_percentage": -3.35406,
      "sparkScore": 40,
      "circulating_supply": 6032609839.413793,
      "total_supply": 6032609839.413793
    },
    {
      "symbol": "XLM",
      "name": "Stellar",
      "price": 0.158847,
      "change24h": 6.71929,
      "marketCap": 5234926666,
      "volume24h": 156201362,
      "ath": 0.875563,
      "ath_change_percentage": -81.9087,
      "sparkScore": 46,
      "circulating_supply": 32955620309.90031,
      "total_supply": 50001786883.65895
    },
    {
      "symbol": "USD1",
      "name": "USD1",
      "price": 0.99911,
      "change24h": -0.02791,
      "marketCap": 4707568653,
      "volume24h": 1953707933,
      "ath": 1.025,
      "ath_change_percentage": -2.556,
      "sparkScore": 59,
      "circulating_supply": 4711762488.991394,
      "total_supply": 4711762488.991394
    },
    {
      "symbol": "RAIN",
      "name": "Rain",
      "price": 0.00902584,
      "change24h": -2.00655,
      "marketCap": 4318649421,
      "volume24h": 30991189,
      "ath": 0.01090099,
      "ath_change_percentage": -17.20433,
      "sparkScore": 35,
      "circulating_supply": 477934311106.1234,
      "total_supply": 1149928975276.78
    },
    {
      "symbol": "HBAR",
      "name": "Hedera",
      "price": 0.099629,
      "change24h": 5.39017,
      "marketCap": 4284399349,
      "volume24h": 139690235,
      "ath": 0.569229,
      "ath_change_percentage": -82.55039,
      "sparkScore": 46,
      "circulating_supply": 43003421564.43284,
      "total_supply": 50000000000.0
    },
    {
      "symbol": "PYUSD",
      "name": "PayPal USD",
      "price": 1.0,
      "change24h": 0.02597,
      "marketCap": 4204192621,
      "volume24h": 97094067,
      "ath": 1.021,
      "ath_change_percentage": -2.01572,
      "sparkScore": 43,
      "circulating_supply": 4203341568.874555,
      "total_supply": 4203341568.874555
    },
    {
      "symbol": "DAI",
      "name": "Dai",
      "price": 1.001,
      "change24h": 0.09254,
      "marketCap": 4179055455,
      "volume24h": 61191372,
      "ath": 1.22,
      "ath_change_percentage": -17.99756,
      "sparkScore": 43,
      "circulating_supply": 4176604485.276116,
      "total_supply": 4176604485.276116
    },
    {
      "symbol": "LTC",
      "name": "Litecoin",
      "price": 54.14,
      "change24h": 4.34911,
      "marketCap": 4162416069,
      "volume24h": 332811084,
      "ath": 410.26,
      "ath_change_percentage": -86.83414,
      "sparkScore": 60,
      "circulating_supply": 76897520.73347135,
      "total_supply": 76901808.23347135
    },
    {
      "symbol": "AVAX",
      "name": "Avalanche",
      "price": 9.16,
      "change24h": 8.13638,
      "marketCap": 3954424578,
      "volume24h": 461628861,
      "ath": 144.96,
      "ath_change_percentage": -93.69245,
      "sparkScore": 63,
      "circulating_supply": 431771961.1772119,
      "total_supply": 463441061.1772119
    },
    {
      "symbol": "ZEC",
      "name": "Zcash",
      "price": 223.78,
      "change24h": 9.40006,
      "marketCap": 3708479740,
      "volume24h": 359168695,
      "ath": 3191.93,
      "ath_change_percentage": -92.98906,
      "sparkScore": 67,
      "circulating_supply": 16578443.9155448,
      "total_supply": 16578828.2905448
    },
    {
      "symbol": "SUI",
      "name": "Sui",
      "price": 0.912657,
      "change24h": 8.83914,
      "marketCap": 3557511566,
      "volume24h": 1069084011,
      "ath": 5.35,
      "ath_change_percentage": -82.93004,
      "sparkScore": 61,
      "circulating_supply": 3899984688.415443,
      "total_supply": 10000000000.0
    },
    {
      "symbol": "SHIB",
      "name": "Shiba Inu",
      "price": 5.71e-06,
      "change24h": 4.27683,
      "marketCap": 3360398445,
      "volume24h": 144824738,
      "ath": 8.616e-05,
      "ath_change_percentage": -93.37252,
      "sparkScore": 48,
      "circulating_supply": 589243817187937.9,
      "total_supply": 589500358955066.1
    },
    {
      "symbol": "CRO",
      "name": "Cronos",
      "price": 0.075964,
      "change24h": 5.22716,
      "marketCap": 3117647730,
      "volume24h": 12721970,
      "ath": 0.965407,
      "ath_change_percentage": -92.13571,
      "sparkScore": 36,
      "circulating_supply": 41068093716.22328,
      "total_supply": 98434575410.70036
    },
    {
      "symbol": "WLFI",
      "name": "World Liberty Financial",
      "price": 0.110434,
      "change24h": 3.41087,
      "marketCap": 3055851035,
      "volume24h": 78209905,
      "ath": 0.331336,
      "ath_change_percentage": -66.66998,
      "sparkScore": 44,
      "circulating_supply": 27661093869.0,
      "total_supply": 100000000000.0
    },
    {
      "symbol": "TON",
      "name": "Toncoin",
      "price": 1.24,
      "change24h": 0.21315,
      "marketCap": 3038203838,
      "volume24h": 90163384,
      "ath": 8.25,
      "ath_change_percentage": -84.99976,
      "sparkScore": 46,
      "circulating_supply": 2452507733.96652,
      "total_supply": 5155492645.490632
    },
    {
      "symbol": "XAUT",
      "name": "Tether Gold",
      "price": 5308.68,
      "change24h": -1.18176,
      "marketCap": 2917094036,
      "volume24h": 1190468303,
      "ath": 5596.7,
      "ath_change_percentage": -5.18906,
      "sparkScore": 66,
      "circulating_supply": 549548.641696,
      "total_supply": 712747.089
    },
    {
      "symbol": "DOT",
      "name": "Polkadot",
      "price": 1.58,
      "change24h": 6.61245,
      "marketCap": 2641077536,
      "volume24h": 340891521,
      "ath": 54.98,
      "ath_change_percentage": -97.12638,
      "sparkScore": 62,
      "circulating_supply": 1670213943.301236,
      "total_supply": 1670213943.301236
    },
    {
      "symbol": "M",
      "name": "MemeCore",
      "price": 1.49,
      "change24h": 2.06136,
      "marketCap": 2595525288,
      "volume24h": 8163513,
      "ath": 2.96,
      "ath_change_percentage": -49.68336,
      "sparkScore": 33,
      "circulating_supply": 1741086084.872817,
      "total_supply": 5341055300.830788
    },
    {
      "symbol": "PAXG",
      "name": "PAX Gold",
      "price": 5374.13,
      "change24h": -1.15545,
      "marketCap": 2545051626,
      "volume24h": 1176382352,
      "ath": 5619.09,
      "ath_change_percentage": -4.45157,
      "sparkScore": 66,
      "circulating_supply": 473805.587,
      "total_supply": 473805.587
    },
    {
      "symbol": "UNI",
      "name": "Uniswap",
      "price": 3.79,
      "change24h": 5.6201,
      "marketCap": 2401499292,
      "volume24h": 291638201,
      "ath": 44.92,
      "ath_change_percentage": -91.5693,
      "sparkScore": 62,
      "circulating_supply": 633561603.6037512,
      "total_supply": 898518420.0366304
    },
    {
      "symbol": "MNT",
      "name": "Mantle",
      "price": 0.641514,
      "change24h": 4.32759,
      "marketCap": 2086616111,
      "volume24h": 34351038,
      "ath": 2.86,
      "ath_change_percentage": -77.56172,
      "sparkScore": 38,
      "circulating_supply": 3252944055.53684,
      "total_supply": 6219316794.889999
    },
    {
      "symbol": "BUIDL",
      "name": "BlackRock USD Institutional Digital Liquidity Fund",
      "price": 1.0,
      "change24h": 0.0,
      "marketCap": 1958775991,
      "volume24h": 0.0,
      "ath": 1.0,
      "ath_change_percentage": 0.0,
      "sparkScore": 24,
      "circulating_supply": 1958775991.060449,
      "total_supply": 1958775991.060449
    },
    {
      "symbol": "USYC",
      "name": "Circle USYC",
      "price": 1.12,
      "change24h": 0.00016,
      "marketCap": 1883793196,
      "volume24h": 111690,
      "ath": 1.12,
      "ath_change_percentage": -0.11521,
      "sparkScore": 29,
      "circulating_supply": 1686626242.240764,
      "total_supply": 1686626242.240764
    },
    {
      "symbol": "USDG",
      "name": "Global Dollar",
      "price": 0.999982,
      "change24h": -0.00464,
      "marketCap": 1767530153,
      "volume24h": 33663557,
      "ath": 1.65,
      "ath_change_percentage": -39.55859,
      "sparkScore": 37,
      "circulating_supply": 1767447249.745451,
      "total_supply": 1767447249.745451
    },
    {
      "symbol": "ASTER",
      "name": "Aster",
      "price": 0.715139,
      "change24h": 4.37556,
      "marketCap": 1756121109,
      "volume24h": 141332234,
      "ath": 2.41,
      "ath_change_percentage": -70.31062,
      "sparkScore": 56,
      "circulating_supply": 2454947754.91,
      "total_supply": 7822985112.003392
    },
    {
      "symbol": "AAVE",
      "name": "Aave",
      "price": 114.83,
      "change24h": 8.50928,
      "marketCap": 1744006943,
      "volume24h": 309443903,
      "ath": 661.69,
      "ath_change_percentage": -82.68491,
      "sparkScore": 68,
      "circulating_supply": 15191820.723606456,
      "total_supply": 16000000.0
    },
    {
      "symbol": "USDF",
      "name": "Falcon USD",
      "price": 0.99602,
      "change24h": -0.03011,
      "marketCap": 1735203698,
      "volume24h": 1160805,
      "ath": 1.075,
      "ath_change_percentage": -7.31621,
      "sparkScore": 30,
      "circulating_supply": 1742008599.959778,
      "total_supply": 1742008599.959778
    },
    {
      "symbol": "TAO",
      "name": "Bittensor",
      "price": 180.13,
      "change24h": 7.80437,
      "marketCap": 1728020385,
      "volume24h": 109206254,
      "ath": 757.6,
      "ath_change_percentage": -76.29508,
      "sparkScore": 60,
      "circulating_supply": 9597491.0,
      "total_supply": 21000000.0
    },
    {
      "symbol": "OKB",
      "name": "OKB",
      "price": 76.58,
      "change24h": 5.0015,
      "marketCap": 1607898364,
      "volume24h": 14839684,
      "ath": 255.5,
      "ath_change_percentage": -70.07282,
      "sparkScore": 41,
      "circulating_supply": 21000000.0,
      "total_supply": 21000000.0
    },
    {
      "symbol": "PI",
      "name": "Pi Network",
      "price": 0.169505,
      "change24h": 3.777,
      "marketCap": 1595247974,
      "volume24h": 17644811,
      "ath": 2.99,
      "ath_change_percentage": -94.33044,
      "sparkScore": 37,
      "circulating_supply": 9412361248.214832,
      "total_supply": 14480555766.48435
    },
    {
      "symbol": "SKY",
      "name": "Sky",
      "price": 0.068494,
      "change24h": 6.77252,
      "marketCap": 1576706018,
      "volume24h": 11955199,
      "ath": 0.100535,
      "ath_change_percentage": -31.94631,
      "sparkScore": 37,
      "circulating_supply": 23016392114.950283,
      "total_supply": 23462665147.36596
    },
    {
      "symbol": "NEAR",
      "name": "NEAR Protocol",
      "price": 1.17,
      "change24h": 11.86809,
      "marketCap": 1512886503,
      "volume24h": 346114289,
      "ath": 20.44,
      "ath_change_percentage": -94.26258,
      "sparkScore": 63,
      "circulating_supply": 1289016660.0,
      "total_supply": 1289016660.0
    },
    {
      "symbol": "BGB",
      "name": "Bitget Token",
      "price": 2.16,
      "change24h": 0.70763,
      "marketCap": 1510013089,
      "volume24h": 19132781,
      "ath": 8.45,
      "ath_change_percentage": -74.48689,
      "sparkScore": 38,
      "circulating_supply": 699992035.9787906,
      "total_supply": 916931610.9787906
    },
    {
      "symbol": "PEPE",
      "name": "Pepe",
      "price": 3.58e-06,
      "change24h": 3.62156,
      "marketCap": 1506392006,
      "volume24h": 375883660,
      "ath": 2.803e-05,
      "ath_change_percentage": -87.22849,
      "sparkScore": 59,
      "circulating_supply": 420690000000000.0,
      "total_supply": 420690000000000.0
    },
    {
      "symbol": "RLUSD",
      "name": "Ripple USD",
      "price": 1.0,
      "change24h": 0.0344,
      "marketCap": 1494456240,
      "volume24h": 95270767,
      "ath": 1.073,
      "ath_change_percentage": -6.8051,
      "sparkScore": 51,
      "circulating_supply": 1495023851.127495,
      "total_supply": 1495023851.127495
    },
    {
      "symbol": "HTX",
      "name": "HTX DAO",
      "price": 1.53e-06,
      "change24h": -2.59607,
      "marketCap": 1398650565,
      "volume24h": 32245324,
      "ath": 3.75e-06,
      "ath_change_percentage": -59.32018,
      "sparkScore": 39,
      "circulating_supply": 916533066327098.8,
      "total_supply": 916533066327098.8
    },
    {
      "symbol": "ETC",
      "name": "Ethereum Classic",
      "price": 8.67,
      "change24h": 5.57517,
      "marketCap": 1351073754,
      "volume24h": 60638780,
      "ath": 167.09,
      "ath_change_percentage": -94.81919,
      "sparkScore": 51,
      "circulating_supply": 155721928.0716566,
      "total_supply": 155721928.0716566
    },
    {
      "symbol": "BFUSD",
      "name": "BFUSD",
      "price": 0.999214,
      "change24h": -0.02011,
      "marketCap": 1319118320,
      "volume24h": 4789983,
      "ath": 1.007,
      "ath_change_percentage": -0.75754,
      "sparkScore": 30,
      "circulating_supply": 1320000000.0,
      "total_supply": 1320000000.0
    },
    {
      "symbol": "ICP",
      "name": "Internet Computer",
      "price": 2.39,
      "change24h": 4.43976,
      "marketCap": 1316318162,
      "volume24h": 80347375,
      "ath": 700.65,
      "ath_change_percentage": -99.65809,
      "sparkScore": 54,
      "circulating_supply": 549325120.4015204,
      "total_supply": 549325120.4015204
    },
    {
      "symbol": "ONDO",
      "name": "Ondo",
      "price": 0.260582,
      "change24h": 7.58977,
      "marketCap": 1267667176,
      "volume24h": 67314171,
      "ath": 2.14,
      "ath_change_percentage": -87.82417,
      "sparkScore": 51,
      "circulating_supply": 4869330647.0,
      "total_supply": 10000000000.0
    },
    {
      "symbol": "USTB",
      "name": "Superstate Short Duration U.S. Government Securities Fund (USTB)",
      "price": 11.0,
      "change24h": 0.0,
      "marketCap": 1157771923,
      "volume24h": 0.0,
      "ath": 11.0,
      "ath_change_percentage": 0.0,
      "sparkScore": 28,
      "circulating_supply": 105218313.568059,
      "total_supply": 105218313.568059
    },
    {
      "symbol": "PUMP",
      "name": "Pump.fun",
      "price": 0.00193203,
      "change24h": 9.73187,
      "marketCap": 1139895156,
      "volume24h": 121194997,
      "ath": 0.00881908,
      "ath_change_percentage": -78.09267,
      "sparkScore": 61,
      "circulating_supply": 590000000000.0,
      "total_supply": 999989194649.1941
    },
    {
      "symbol": "POL",
      "name": "POL (ex-MATIC)",
      "price": 0.107517,
      "change24h": 5.36995,
      "marketCap": 1139449981,
      "volume24h": 69745460,
      "ath": 1.29,
      "ath_change_percentage": -91.65555,
      "sparkScore": 52,
      "circulating_supply": 10600201639.81838,
      "total_supply": 10600201639.81838
    },
    {
      "symbol": "GT",
      "name": "Gate",
      "price": 7.01,
      "change24h": 5.85584,
      "marketCap": 1133103428,
      "volume24h": 3032092,
      "ath": 25.94,
      "ath_change_percentage": -72.94929,
      "sparkScore": 33,
      "circulating_supply": 115180573.04885802,
      "total_supply": 115180573.04885802
    },
    {
      "symbol": "WLD",
      "name": "Worldcoin",
      "price": 0.391219,
      "change24h": 7.37687,
      "marketCap": 1124631375,
      "volume24h": 86055035,
      "ath": 11.74,
      "ath_change_percentage": -96.6771,
      "sparkScore": 56,
      "circulating_supply": 2877366571.941048,
      "total_supply": 10000000000.0
    },
    {
      "symbol": "KCS",
      "name": "KuCoin",
      "price": 7.74,
      "change24h": 7.50022,
      "marketCap": 1024085639,
      "volume24h": 4824711,
      "ath": 28.83,
      "ath_change_percentage": -73.1011,
      "sparkScore": 34,
      "circulating_supply": 132155021.7355671,
      "total_supply": 142155021.7355671
    },
    {
      "symbol": "NIGHT",
      "name": "Midnight",
      "price": 0.058734,
      "change24h": 2.80029,
      "marketCap": 976804547,
      "volume24h": 10539777,
      "ath": 0.118529,
      "ath_change_percentage": -50.41504,
      "sparkScore": 32,
      "circulating_supply": 16607399400.63495,
      "total_supply": 24000000000.0
    },
    {
      "symbol": "HASH",
      "name": "Provenance Blockchain",
      "price": 0.01767487,
      "change24h": 2.23695,
      "marketCap": 976227036,
      "volume24h": 25744,
      "ath": 0.060147,
      "ath_change_percentage": -70.57861,
      "sparkScore": 20,
      "circulating_supply": 55166310774.0,
      "total_supply": 100000000000.0
    },
    {
      "symbol": "MORPHO",
      "name": "Morpho",
      "price": 1.71,
      "change24h": -3.50319,
      "marketCap": 937051696,
      "volume24h": 27734489,
      "ath": 4.17,
      "ath_change_percentage": -59.11016,
      "sparkScore": 38,
      "circulating_supply": 548681115.2642183,
      "total_supply": 1000000000.0
    },
    {
      "symbol": "QNT",
      "name": "Quant",
      "price": 63.28,
      "change24h": 4.59064,
      "marketCap": 920279445,
      "volume24h": 12797037,
      "ath": 427.42,
      "ath_change_percentage": -85.21502,
      "sparkScore": 37,
      "circulating_supply": 14544176.164081175,
      "total_supply": 14612493.0
    },
    {
      "symbol": "ATOM",
      "name": "Cosmos Hub",
      "price": 1.84,
      "change24h": 3.56749,
      "marketCap": 914348973,
      "volume24h": 50140735,
      "ath": 44.45,
      "ath_change_percentage": -95.85712,
      "sparkScore": 48,
      "circulating_supply": 495736797.585837,
      "total_supply": 495736797.585837
    },
    {
      "symbol": "ENA",
      "name": "Ethena",
      "price": 0.104929,
      "change24h": 9.69133,
      "marketCap": 862865411,
      "volume24h": 104772262,
      "ath": 1.52,
      "ath_change_percentage": -93.1149,
      "sparkScore": 57,
      "circulating_supply": 8225000000.0,
      "total_supply": 15000000000.0
    },
    {
      "symbol": "NEXO",
      "name": "NEXO",
      "price": 0.852614,
      "change24h": 3.18972,
      "marketCap": 852853433,
      "volume24h": 9832093,
      "ath": 4.07,
      "ath_change_percentage": -78.97237,
      "sparkScore": 29,
      "circulating_supply": 1000000000.0,
      "total_supply": 1000000000.0
    },
    {
      "symbol": "USDTB",
      "name": "USDtb",
      "price": 0.999706,
      "change24h": -0.05534,
      "marketCap": 835500565,
      "volume24h": 641977,
      "ath": 1.057,
      "ath_change_percentage": -5.3299,
      "sparkScore": 23,
      "circulating_supply": 835268729.4261826,
      "total_supply": 835268729.4261826
    },
    {
      "symbol": "TRUMP",
      "name": "Official Trump",
      "price": 3.5,
      "change24h": 7.15923,
      "marketCap": 813805657,
      "volume24h": 167832511,
      "ath": 73.43,
      "ath_change_percentage": -95.24202,
      "sparkScore": 58,
      "circulating_supply": 232498807.465716,
      "total_supply": 1000000000.0
    },
    {
      "symbol": "FLR",
      "name": "Flare",
      "price": 0.0094524,
      "change24h": 7.71065,
      "marketCap": 802137417,
      "volume24h": 4337321,
      "ath": 0.150073,
      "ath_change_percentage": -93.71725,
      "sparkScore": 29,
      "circulating_supply": 84988003676.23932,
      "total_supply": 105082054910.5706
    },
    {
      "symbol": "KAS",
      "name": "Kaspa",
      "price": 0.02981521,
      "change24h": 4.95486,
      "marketCap": 798796737,
      "volume24h": 16674877,
      "ath": 0.207411,
      "ath_change_percentage": -85.62766,
      "sparkScore": 35,
      "circulating_supply": 26777148610.50726,
      "total_supply": 27244208138.6294
    },
    {
      "symbol": "EUTBL",
      "name": "Spiko EU T-Bills Money Market Fund",
      "price": 1.24,
      "change24h": 0.00839,
      "marketCap": 796450735,
      "volume24h": 0.0,
      "ath": 1.26,
      "ath_change_percentage": -1.81131,
      "sparkScore": 22,
      "circulating_supply": 643244970.87733,
      "total_supply": 643244970.87733
    },
    {
      "symbol": "ALGO",
      "name": "Algorand",
      "price": 0.087802,
      "change24h": 6.33274,
      "marketCap": 780435745,
      "volume24h": 32905750,
      "ath": 3.56,
      "ath_change_percentage": -97.53661,
      "sparkScore": 40,
      "circulating_supply": 8885774791.695772,
      "total_supply": 8885774791.695772
    },
    {
      "symbol": "OUSG",
      "name": "OUSG",
      "price": 114.44,
      "change24h": 0.0,
      "marketCap": 754281618,
      "volume24h": 0.0,
      "ath": 114.44,
      "ath_change_percentage": 0.0,
      "sparkScore": 27,
      "circulating_supply": 6591064.488913452,
      "total_supply": 6591064.488913452
    },
    {
      "symbol": "APT",
      "name": "Aptos",
      "price": 0.951176,
      "change24h": 7.44467,
      "marketCap": 741416731,
      "volume24h": 111357722,
      "ath": 19.92,
      "ath_change_percentage": -95.24038,
      "sparkScore": 56,
      "circulating_supply": 780272646.7319334,
      "total_supply": 1197871786.052126
    },
    {
      "symbol": "FIL",
      "name": "Filecoin",
      "price": 0.977475,
      "change24h": 4.8356,
      "marketCap": 738374468,
      "volume24h": 109523073,
      "ath": 236.84,
      "ath_change_percentage": -99.58811,
      "sparkScore": 56,
      "circulating_supply": 755885095.0,
      "total_supply": 1958221727.0
    },
    {
      "symbol": "JAAA",
      "name": "Janus Henderson Anemoy AAA CLO Fund",
      "price": 1.028,
      "change24h": 0.0,
      "marketCap": 732173788,
      "volume24h": 0.0,
      "ath": 1.028,
      "ath_change_percentage": 0.0,
      "sparkScore": 22,
      "circulating_supply": 712528659.890913,
      "total_supply": 712528659.890913
    },
    {
      "symbol": "USDD",
      "name": "USDD",
      "price": 0.999728,
      "change24h": 0.0472,
      "marketCap": 727387514,
      "volume24h": 2821844,
      "ath": 1.052,
      "ath_change_percentage": -4.9454,
      "sparkScore": 26,
      "circulating_supply": 727506518.95,
      "total_supply": 727506518.95
    },
    {
      "symbol": "RENDER",
      "name": "Render",
      "price": 1.38,
      "change24h": 4.69599,
      "marketCap": 715112330,
      "volume24h": 62404409,
      "ath": 13.53,
      "ath_change_percentage": -89.83811,
      "sparkScore": 55,
      "circulating_supply": 518743261.0140742,
      "total_supply": 533503434.2940742
    },
    {
      "symbol": "USDY",
      "name": "Ondo US Dollar Yield",
      "price": 1.11,
      "change24h": -1.09574,
      "marketCap": 703851261,
      "volume24h": 160902,
      "ath": 1.26,
      "ath_change_percentage": -11.63372,
      "sparkScore": 25,
      "circulating_supply": 634129769.9058918,
      "total_supply": 1169642471.259184
    },
    {
      "symbol": "STABLE",
      "name": "\u200b\u200bStable",
      "price": 0.03325719,
      "change24h": 9.88939,
      "marketCap": 680313832,
      "volume24h": 46605280,
      "ath": 0.0388874,
      "ath_change_percentage": -14.63497,
      "sparkScore": 46,
      "circulating_supply": 20470350137.0,
      "total_supply": 100000000000.0
    },
    {
      "symbol": "XDC",
      "name": "XDC Network",
      "price": 0.03310592,
      "change24h": 0.2382,
      "marketCap": 660223108,
      "volume24h": 15151306,
      "ath": 0.192754,
      "ath_change_percentage": -82.83153,
      "sparkScore": 34,
      "circulating_supply": 19934954902.92,
      "total_supply": 38053963864.95
    },
    {
      "symbol": "VET",
      "name": "VeChain",
      "price": 0.0072653,
      "change24h": 5.53765,
      "marketCap": 625142626,
      "volume24h": 23571774,
      "ath": 0.280991,
      "ath_change_percentage": -97.42152,
      "sparkScore": 38,
      "circulating_supply": 85985041177.0,
      "total_supply": 85985041177.0
    },
    {
      "symbol": "BDX",
      "name": "Beldex",
      "price": 0.081302,
      "change24h": 1.6253,
      "marketCap": 618205107,
      "volume24h": 11625929,
      "ath": 0.450785,
      "ath_change_percentage": -81.95599,
      "sparkScore": 34,
      "circulating_supply": 7605900969.463922,
      "total_supply": 9936200048.803179
    },
    {
      "symbol": "ARB",
      "name": "Arbitrum",
      "price": 0.101349,
      "change24h": 8.62922,
      "marketCap": 601454550,
      "volume24h": 128725710,
      "ath": 2.39,
      "ath_change_percentage": -95.78066,
      "sparkScore": 57,
      "circulating_supply": 5939074958.0,
      "total_supply": 10000000000.0
    },
    {
      "symbol": "JUP",
      "name": "Jupiter",
      "price": 0.170954,
      "change24h": 16.8829,
      "marketCap": 598581829,
      "volume24h": 53656567,
      "ath": 2.0,
      "ath_change_percentage": -91.44414,
      "sparkScore": 57,
      "circulating_supply": 3497363517.1,
      "total_supply": 6863982739.225857
    },
    {
      "symbol": "PIPPIN",
      "name": "pippin",
      "price": 0.593994,
      "change24h": -2.83771,
      "marketCap": 594614075,
      "volume24h": 48549056,
      "ath": 0.897199,
      "ath_change_percentage": -34.15791,
      "sparkScore": 47,
      "circulating_supply": 999937480.835205,
      "total_supply": 999937480.835205
    },
    {
      "symbol": "JTRSY",
      "name": "Janus Henderson Anemoy Treasury Fund",
      "price": 1.096,
      "change24h": 0.0,
      "marketCap": 567936077,
      "volume24h": 0.0,
      "ath": 1.096,
      "ath_change_percentage": 0.0,
      "sparkScore": 22,
      "circulating_supply": 518328892.305495,
      "total_supply": 518328892.305495
    },
    {
      "symbol": "USD0",
      "name": "Usual USD",
      "price": 0.997337,
      "change24h": -0.13767,
      "marketCap": 566043289,
      "volume24h": 349522,
      "ath": 1.33,
      "ath_change_percentage": -24.93072,
      "sparkScore": 23,
      "circulating_supply": 564489434.4129121,
      "total_supply": 564489434.4129121
    },
    {
      "symbol": "DCR",
      "name": "Decred",
      "price": 31.5,
      "change24h": 11.11763,
      "marketCap": 545284557,
      "volume24h": 8960055,
      "ath": 247.35,
      "ath_change_percentage": -87.27091,
      "sparkScore": 36,
      "circulating_supply": 17299386.56653042,
      "total_supply": 17299386.56653042
    },
    {
      "symbol": "GHO",
      "name": "GHO",
      "price": 1.0,
      "change24h": -0.00771,
      "marketCap": 527450895,
      "volume24h": 1340963,
      "ath": 1.03,
      "ath_change_percentage": -2.88279,
      "sparkScore": 26,
      "circulating_supply": 527437881.796613,
      "total_supply": 527437881.796613
    },
    {
      "symbol": "BONK",
      "name": "Bonk",
      "price": 5.95e-06,
      "change24h": 6.78803,
      "marketCap": 522764750,
      "volume24h": 68451381,
      "ath": 5.825e-05,
      "ath_change_percentage": -89.81265,
      "sparkScore": 56,
      "circulating_supply": 87995150573675.28,
      "total_supply": 87995150575169.48
    },
    {
      "symbol": "A7A5",
      "name": "A7A5",
      "price": 0.01288349,
      "change24h": 0.56302,
      "marketCap": 504943063,
      "volume24h": 1336.92,
      "ath": 0.229635,
      "ath_change_percentage": -94.38984,
      "sparkScore": 20,
      "circulating_supply": 39192750985.66073,
      "total_supply": 39192750985.66073
    },
    {
      "symbol": "TUSD",
      "name": "TrueUSD",
      "price": 0.999471,
      "change24h": 0.14202,
      "marketCap": 494463798,
      "volume24h": 7511866,
      "ath": 1.62,
      "ath_change_percentage": -38.25697,
      "sparkScore": 29,
      "circulating_supply": 494515083.0,
      "total_supply": 494515083.0
    },
    {
      "symbol": "STX",
      "name": "Stacks",
      "price": 0.258708,
      "change24h": 6.37935,
      "marketCap": 474017026,
      "volume24h": 15312004,
      "ath": 3.86,
      "ath_change_percentage": -93.33705,
      "sparkScore": 38,
      "circulating_supply": 1832253306.45942,
      "total_supply": 1832253306.45942
    }
  ],
  "new_coins": [
    {
      "symbol": "JUP",
      "name": "Jupiter",
      "price": 0.170954,
      "change24h": 16.8829,
      "marketCap": 598581829,
      "volume24h": 53656567,
      "ath": 2.0,
      "ath_change_percentage": -91.44414,
      "sparkScore": 57,
      "circulating_supply": 3497363517.1,
      "total_supply": 6863982739.225857,
      "new_score": 88.48739016954468,
      "listed_since": "today",
      "potential": "high"
    },
    {
      "symbol": "USD1",
      "name": "USD1",
      "price": 0.99911,
      "change24h": -0.02791,
      "marketCap": 4707568653,
      "volume24h": 1953707933,
      "ath": 1.025,
      "ath_change_percentage": -2.556,
      "sparkScore": 59,
      "circulating_supply": 4711762488.991394,
      "total_supply": 4711762488.991394,
      "new_score": 87.1849881200011,
      "listed_since": "today",
      "potential": "high"
    },
    {
      "symbol": "XAUT",
      "name": "Tether Gold",
      "price": 5308.68,
      "change24h": -1.18176,
      "marketCap": 2917094036,
      "volume24h": 1190468303,
      "ath": 5596.7,
      "ath_change_percentage": -5.18906,
      "sparkScore": 66,
      "circulating_supply": 549548.641696,
      "total_supply": 712747.089,
      "new_score": 87.05319302628018,
      "listed_since": "today",
      "potential": "high"
    },
    {
      "symbol": "RLUSD",
      "name": "Ripple USD",
      "price": 1.0,
      "change24h": 0.0344,
      "marketCap": 1494456240,
      "volume24h": 95270767,
      "ath": 1.073,
      "ath_change_percentage": -6.8051,
      "sparkScore": 51,
      "circulating_supply": 1495023851.127495,
      "total_supply": 1495023851.127495,
      "new_score": 85.87138983173405,
      "listed_since": "today",
      "potential": "high"
    },
    {
      "symbol": "TAO",
      "name": "Bittensor",
      "price": 180.13,
      "change24h": 7.80437,
      "marketCap": 1728020385,
      "volume24h": 109206254,
      "ath": 757.6,
      "ath_change_percentage": -76.29508,
      "sparkScore": 60,
      "circulating_supply": 9597491.0,
      "total_supply": 21000000.0,
      "new_score": 85.02535158202271,
      "listed_since": "today",
      "potential": "high"
    }
  ],
  "total_coins": 100
}