[
  {
    "symbol": "LINK",
    "name": "Chainlink",
    "activity": "Wallet Accumulation",
    "direction": "bullish",
    "amount_usd": 47966535,
    "amount_coins": 3639342.53,
    "significance": "high",
    "confidence": 0.78,
    "timestamp": "2026-01-03T19:15:15.931117"
  },
  {
    "symbol": "ADA",
    "name": "Cardano",
    "activity": "Large Buy",
    "direction": "bullish",
    "amount_usd": 47659631,
    "amount_coins": 122865766.15,
    "significance": "high",
    "confidence": 0.94,
    "timestamp": "2026-01-03T19:15:15.931085"
  },
  {
    "symbol": "XRP",
    "name": "XRP",
    "activity": "Exchange Withdrawal",
    "direction": "bullish",
    "amount_usd": 39960949,
    "amount_coins": 19980474.74,
    "significance": "medium",
    "confidence": 0.8,
    "timestamp": "2026-01-03T19:15:15.931070"
  },
  {
    "symbol": "SOL",
    "name": "Solana",
    "activity": "Large Sell",
    "direction": "bearish",
    "amount_usd": 8353581,
    "amount_coins": 63433.68,
    "significance": "medium",
    "confidence": 0.71,
    "timestamp": "2026-01-03T19:15:15.931055"
  },
  {
    "symbol": "DOGE",
    "name": "Dogecoin",
    "activity": "Exchange Transfer",
    "direction": "neutral",
    "amount_usd": 3524919,
    "amount_coins": 24919891.72,
    "significance": "medium",
    "confidence": 0.79,
    "timestamp": "2026-01-03T19:15:15.931098"
  }
]