[
  {
    "symbol": "LINK",
    "name": "Chainlink",
    "activity": "Large Buy",
    "direction": "bullish",
    "amount_usd": 25988643,
    "amount_coins": 2479832.39,
    "significance": "high",
    "confidence": 0.75,
    "timestamp": "2026-05-10T11:22:11.706955"
  },
  {
    "symbol": "SOL",
    "name": "Solana",
    "activity": "Large Buy",
    "direction": "bullish",
    "amount_usd": 21968576,
    "amount_coins": 234782.26,
    "significance": "medium",
    "confidence": 0.87,
    "timestamp": "2026-05-10T11:22:11.706861"
  },
  {
    "symbol": "ADA",
    "name": "Cardano",
    "activity": "Wallet Accumulation",
    "direction": "bullish",
    "amount_usd": 9453933,
    "amount_coins": 34714733.28,
    "significance": "medium",
    "confidence": 0.93,
    "timestamp": "2026-05-10T11:22:11.706916"
  },
  {
    "symbol": "DOGE",
    "name": "Dogecoin",
    "activity": "Large Buy",
    "direction": "bullish",
    "amount_usd": 4609998,
    "amount_coins": 42577539.95,
    "significance": "medium",
    "confidence": 0.74,
    "timestamp": "2026-05-10T11:22:11.706936"
  }
]