[
  {
    "symbol": "DOGE",
    "name": "Dogecoin",
    "activity": "Exchange Transfer",
    "direction": "neutral",
    "amount_usd": 48274998,
    "amount_coins": 425259191.46,
    "significance": "high",
    "confidence": 0.86,
    "timestamp": "2026-05-05T18:34:46.717084"
  },
  {
    "symbol": "ADA",
    "name": "Cardano",
    "activity": "Exchange Transfer",
    "direction": "neutral",
    "amount_usd": 45314645,
    "amount_coins": 175557184.84,
    "significance": "high",
    "confidence": 0.72,
    "timestamp": "2026-05-05T18:34:46.717068"
  },
  {
    "symbol": "LINK",
    "name": "Chainlink",
    "activity": "Wallet Accumulation",
    "direction": "bullish",
    "amount_usd": 42986427,
    "amount_coins": 4431590.39,
    "significance": "high",
    "confidence": 0.73,
    "timestamp": "2026-05-05T18:34:46.717104"
  },
  {
    "symbol": "SOL",
    "name": "Solana",
    "activity": "Large Buy",
    "direction": "bullish",
    "amount_usd": 36693794,
    "amount_coins": 428565.68,
    "significance": "medium",
    "confidence": 0.94,
    "timestamp": "2026-05-05T18:34:46.717015"
  },
  {
    "symbol": "XRP",
    "name": "XRP",
    "activity": "Exchange Transfer",
    "direction": "neutral",
    "amount_usd": 14487339,
    "amount_coins": 10274708.64,
    "significance": "medium",
    "confidence": 0.77,
    "timestamp": "2026-05-05T18:34:46.717031"
  }
]